{
  "scientific_name": "Amanita muscaria",
  "author_citation": "(L.) Lam. 1783",
  "accepted_name": "Amanita muscaria",
  "basionym": "Agaricus muscarius L.",
  "protonym": "Agaricus muscarius",
  
  "taxonomy_domain": "Eukaryota",
  "taxonomy_kingdom": "Fungi",
  "taxonomy_phylum": "Basidiomycota",
  "taxonomy_class": "Agaricomycetes",
  "taxonomy_order": "Agaricales",
  "taxonomy_family": "Amanitaceae",
  "taxonomy_genus": "Amanita",
  "taxonomy_species": "muscaria",
  "taxonomy_subspecies": null,
  "taxonomy_variety": "muscaria",
  
  "synonyms": ["Agaricus muscarius", "Amanita muscaria var. muscaria"],
  "common_names": ["Fly Agaric", "Fly Amanita", "Toadstool"],
  "international_names": {
    "de": "Fliegenpilz",
    "fr": "Amanite tue-mouches",
    "it": "Ovolo malefico",
    "es": "Matamoscas",
    "ru": "Мухомор красный"
  },
  
  "gbif_key": 5259401,
  "inaturalist_taxon_id": 48715,
  "mycobank_id": 505,
  "index_fungorum_id": 505,
  "wikidata_id": "Q158129",
  
  "barcode_marker_primary": "ITS",
  "barcode_its": "ITS1-5.8S-ITS2 (~680bp)",
  "barcode_sequence_length_bp": 680,
  "barcode_quality_score": "HQ",
  "barcode_genbank_accession": "MH123456",
  
  "taxonomy_status": "accepted",
  "uncertainty_level": "confirmed",
  "nomenclatural_code": "ICN",
  
  "quick_id_checklist": [
    "Bright red cap with white warts",
    "White gills, free from stem",
    "White stem with bulbous base and volva",
    "Skirt-like ring on upper stem",
    "No color change when cut"
  ],
  
  "identification_difficulty": "beginner",
  "time_to_identify_minutes": { "min": 1, "max": 3 },
  "minimum_equipment_needed": "none",
  "field_identifiable": true,
  
  "confusion_species_list": [
    { "name": "Amanita caesarea", "type": "lookalike", "risk": "low" },
    { "name": "Amanita pantherina", "type": "similar", "risk": "high" }
  ],
  "confusion_risk_level": { "level": "minor", "label": "Low - Highly distinctive" },
  "confusion_consequences": "dangerous",
  
  "key_differentiating_features": [
    { "feature": "Cap color", "this_species": "Red with white warts", "confusion_species": "Brown (pantherina)" },
    { "feature": "Volva", "this_species": "Warty rings on bulb", "confusion_species": "Distinct cup (caesarea)" }
  ],
  
  "chemical_spot_tests": {
    "koh": { "result": "positive", "color": "yellow on cap" },
    "feso4": { "result": "negative", "color": "no change" }
  },
  
  "spore_print_color": "white",
  "fluorescence_uv": false,
  
  "smell_description": "Faint, slightly earthy",
  "smell_comparable_to": "Raw potato, earth",
  "taste_safe_to_test": false,
  "taste_description": "DO NOT TASTE - toxic species",
  
  "ai_identification_reliability": { "value": 98, "max": 100 },
  "inaturalist_cv_accuracy": 9.8,
  "common_ai_misidentifications": ["Amanita persicina", "Color variants"],
  
  "microscopy_required": false,
  "microscopy_key_features": "Spores broadly ellipsoid, 9-13 × 6.5-9 μm",
  "recommended_magnification": "400x",
  
  "habit": "solitary to scattered",
  "growth_form": "agaricoid",
  "body_plan": "cap and stem with ring and volva",
  "symmetry": "radial",
  
  "size_range_cm": { "min": 8, "max": 20 },
  "size_typical_cm": 12,
  
  "cap_diameter_cm": { "min": 8, "max": 20 },
  "stem_height_cm": { "min": 8, "max": 18 },
  "stem_width_cm": { "min": 1.5, "max": 3 },
  
  "color_primary": "red",
  "color_secondary": "white",
  "color_pattern": "spotted (white warts on red)",
  "color_fresh": "bright scarlet red",
  "color_mature": "orange-red",
  "color_dry": "faded orange",
  
  "consistency_fresh": "firm",
  "consistency_mature": "soft",
  "break_behavior": "clean break",
  
  "smell_fresh": "faint, earthy",
  "smell_intensity": "weak",
  "taste": "TOXIC - do not taste",
  "taste_warning": "DANGER: Contains muscimol and ibotenic acid"
}
